mlwireless/__init__.py
mlwireless/mlwireless.py
mlwireless/plotter.py
mlwireless-0.9.1.dist-info/METADATA
mlwireless-0.9.1.dist-info/WHEEL
mlwireless-0.9.1.dist-info/licenses/LICENSE
mlwireless-0.9.1.dist-info/RECORD
