Metadata-Version: 2.4
Name: mlwireless
Version: 0.9.1
Summary: A comprehensive physical layer simulator for OFDM-MIMO with machine learning capabilities.
Project-URL: Homepage, https://farismismar.com
Project-URL: Repository, https://github.com/farismismar/mlwireless
Project-URL: Issues, https://github.com/farismismar/mlwireless/issues
Author-email: "Faris B. Mismar" <faris.mismar@utexas.edu>
License: Copyright (c) 2021–2025 Faris B. Mismar
License-File: LICENSE
Keywords: machine learning,python,wireless
Classifier: License :: OSI Approved :: BSD License
Classifier: Operating System :: OS Independent
Classifier: Programming Language :: Python :: 3
Requires-Python: >=3.9.13
Requires-Dist: matplotlib>=3.9.4
Requires-Dist: numpy>=1.26.4
Requires-Dist: pandas>=2.2.3
Requires-Dist: scikit-learn>=1.6.1
Requires-Dist: scipy>=1.13.1
Requires-Dist: tensorflow>=2.16.2
